pyzwave/__init__.py
pyzwave/adapter.py
pyzwave/application.py
pyzwave/connection.py
pyzwave/dtlsconnection.py
pyzwave/mailbox.py
pyzwave/message.py
pyzwave/node.py
pyzwave/persistantstorage.py
pyzwave/types.py
pyzwave/util.py
pyzwave/zipconnection.py
pyzwave/zipgateway.py
pyzwave/commandclass/ApplicationStatus.py
pyzwave/commandclass/Association.py
pyzwave/commandclass/AssociationGrpInfo.py
pyzwave/commandclass/Basic.py
pyzwave/commandclass/Battery.py
pyzwave/commandclass/CommandClass.py
pyzwave/commandclass/Configuration.py
pyzwave/commandclass/Indicator.py
pyzwave/commandclass/Mailbox.py
pyzwave/commandclass/ManufacturerSpecific.py
pyzwave/commandclass/Meter.py
pyzwave/commandclass/MultiChannelAssociation.py
pyzwave/commandclass/NetworkManagementInclusion.py
pyzwave/commandclass/NetworkManagementProxy.py
pyzwave/commandclass/NodeProvisioning.py
pyzwave/commandclass/SensorMultilevel.py
pyzwave/commandclass/Supervision.py
pyzwave/commandclass/SwitchBinary.py
pyzwave/commandclass/Version.py
pyzwave/commandclass/Zip.py
pyzwave/commandclass/ZipGateway.py
pyzwave/commandclass/ZipND.py
pyzwave/commandclass/ZwavePlusInfo.py
pyzwave/commandclass/__init__.py
pyzwave/const/ZW_classcmd.py
python_zwave-0.2.1.dist-info/LICENSE
python_zwave-0.2.1.dist-info/METADATA
python_zwave-0.2.1.dist-info/WHEEL
python_zwave-0.2.1.dist-info/top_level.txt
python_zwave-0.2.1.dist-info/RECORD
