Metadata-Version: 2.1
Name: python-zwave
Version: 0.2.1
Summary: Library implementing a Z-Wave stack
Home-page: http://github.com/pyzwave/pyzwave
Author: Micke Prag
Author-email: micke.prag@telldus.se
License: GPL-3.0
Project-URL: Documentation, https://pyzwave.readthedocs.io
Project-URL: Source, http://github.com/pyzwave/pyzwave
Platform: UNKNOWN
Classifier: Development Status :: 3 - Alpha
Classifier: Intended Audience :: Developers
Classifier: License :: OSI Approved :: GNU General Public License v3 (GPLv3)
Classifier: Operating System :: OS Independent
Classifier: Programming Language :: Python :: 3
Classifier: Topic :: Home Automation
Requires-Python: >=3.6
